BiobankRead2/BiobankRead2.py
BiobankRead2/__init__.py
BiobankRead2/data/ICD10_UKB.tsv
BiobankRead2/data/ICD9_codes.csv
BiobankRead2/data/coding19.tsv
BiobankRead2/data/coding3.tsv
BiobankRead2/data/coding6.tsv
BiobankRead2-3.1.data/scripts/extract_HES.py
BiobankRead2-3.1.data/scripts/extract_SR.py
BiobankRead2-3.1.data/scripts/extract_death.py
BiobankRead2-3.1.data/scripts/extract_variables.py
BiobankRead2-3.1.dist-info/LICENSE
BiobankRead2-3.1.dist-info/METADATA
BiobankRead2-3.1.dist-info/WHEEL
BiobankRead2-3.1.dist-info/top_level.txt
BiobankRead2-3.1.dist-info/RECORD
