Metadata-Version: 2.1
Name: BiobankRead2
Version: 3.1
Summary: Python scripts for UKB data
Home-page: UNKNOWN
Author: Deborah Schneider-Luftman
Author-email: ds711@ic.ac.uk
License: GNU GPL v3
Platform: UNKNOWN
Requires-Dist: bs4
Requires-Dist: numpy
Requires-Dist: pandas
Requires-Dist: urllib3
Requires-Dist: regex
Requires-Dist: seaborn
